team_mul/__init__.py
team_mul/mul.py
team_mul-0.1.1.dist-info/METADATA
team_mul-0.1.1.dist-info/WHEEL
team_mul-0.1.1.dist-info/entry_points.txt
team_mul-0.1.1.dist-info/top_level.txt
team_mul-0.1.1.dist-info/RECORD
