Metadata-Version: 2.1
Name: team_mul
Version: 0.1.1
Summary: Default template for PDM package
Author-email: Kimwonjoon <kimpass189@gmail.com>
License: MIT
Requires-Python: >=3.9
